setup.py
vcodeGen/__init__.py
vcodeGen.egg-info/PKG-INFO
vcodeGen.egg-info/SOURCES.txt
vcodeGen.egg-info/dependency_links.txt
vcodeGen.egg-info/top_level.txt