Metadata-Version: 1.0
Name: vcodeGen
Version: 0.1.32
Summary: 轻易地生成图片验证码，防止你的网站被爬虫。
Home-page: https://code.xueersi.com
Author: Ruoyu Wang
Author-email: UNKNOWN
License: UNKNOWN
Platform: UNKNOWN
